{
  "answer_slot_source": "live_api",
  "answer_slot_success": true,
  "answer_slots": {
    "answer_family": "observability_metrics",
    "answer_slot_source": "live_api",
    "api_error": false,
    "api_evidence_state": "live_evidence",
    "api_item_count": 2,
    "api_pagination": [
      {
        "links": {
          "next": "/synthetic/observability_metrics?start=1"
        },
        "page": {
          "limit": 1,
          "start": 0,
          "total": 2
        }
      }
    ],
    "api_parser_modes": [
      "endpoint_family"
    ],
    "counts": [
      "2"
    ],
    "discrepancy": false,
    "dry_run": false,
    "entity_ids": [],
    "entity_names": [],
    "live_api_evidence_available": true,
    "metrics": [],
    "slots_present": [
      "counts",
      "timestamps",
      "api_item_count",
      "live_api_evidence_available",
      "api_evidence_state",
      "answer_slot_source",
      "api_pagination",
      "api_parser_modes",
      "api_items"
    ],
    "sql_row_count": null,
    "statuses": [],
    "timestamps": [
      "2026-03-17T00:00:00Z",
      "2026-03-17T01:00:00Z"
    ]
  },
  "api_error_handled": false,
  "api_evidence_present": true,
  "case": "pagination",
  "empty_live_result_handled": false,
  "endpoint_family": "observability_metrics",
  "endpoint_id": "observability_metrics",
  "evidence_bus": {
    "api_counts": [
      2,
      3,
      3
    ],
    "api_errors": [],
    "api_evidence_states": [
      "live_evidence"
    ],
    "api_ids": [],
    "api_names": [
      "failedBatchCount"
    ],
    "api_pagination": [
      {
        "links": {
          "next": "/synthetic/observability_metrics?start=1"
        },
        "page": {
          "limit": 1,
          "start": 0,
          "total": 2
        }
      }
    ],
    "api_parser_modes": [
      "endpoint_family"
    ],
    "api_statuses": [],
    "api_timestamps": [
      "2026-03-17T00:00:00Z",
      "2026-03-17T01:00:00Z"
    ],
    "counts": [
      {
        "failedBatchCount": 3,
        "total": 2,
        "value": 3
      }
    ],
    "ids": {},
    "names": [],
    "statuses": [],
    "timestamps": [
      "2026-03-17T00:00:00Z",
      "{'timestamp': '2026-03-17T00:00:00Z', 'windowEnd': '2026-03-17T01:00:00Z', 'windowStart': '2026-03-17T00:00:00Z'}"
    ]
  },
  "evidence_state": "live_evidence",
  "evidencebus_forwarded": true,
  "evidencebus_payload_forwarded": true,
  "evidencebus_state_only_forwarded": false,
  "final_answer": "Live API evidence returned 2 item(s).",
  "final_answer_contains_api_supported_field": true,
  "fixture": "[REDACTED]/Desktop/dashsys-workshop-vldb/tests/fixtures/adobe_api_responses/observability_metrics/pagination.json",
  "malformed_response_handled": false,
  "method": "POST",
  "parsed_evidence": {
    "counts": {
      "failedBatchCount": 3,
      "total": 2,
      "value": 3
    },
    "dry_run": false,
    "endpoint": "/data/infrastructure/observability/insights/metrics",
    "endpoint_family": "observability_metrics",
    "endpoint_id": "observability_metrics",
    "errors": [],
    "evidence_state": "live_evidence",
    "ids": [],
    "important_fields": {
      "counts": {
        "failedBatchCount": 3,
        "total": 2,
        "value": 3
      },
      "metric_names": [
        "failedBatchCount"
      ],
      "names": [
        "failedBatchCount"
      ],
      "timestamps": {
        "timestamp": "2026-03-17T00:00:00Z",
        "windowEnd": "2026-03-17T01:00:00Z",
        "windowStart": "2026-03-17T00:00:00Z"
      }
    },
    "items": [
      {
        "metric": "failedBatchCount",
        "timestamp": "2026-03-17T00:00:00Z",
        "value": 3,
        "windowEnd": "2026-03-17T01:00:00Z",
        "windowStart": "2026-03-17T00:00:00Z"
      }
    ],
    "live_evidence_available": true,
    "method": "POST",
    "names": [
      "failedBatchCount"
    ],
    "ok": true,
    "pagination": {
      "links": {
        "next": "/synthetic/observability_metrics?start=1"
      },
      "page": {
        "limit": 1,
        "start": 0,
        "total": 2
      }
    },
    "parser_mode": "endpoint_family",
    "path": "/data/infrastructure/observability/insights/metrics",
    "raw_preview": {
      "links": {
        "next": "/synthetic/observability_metrics?start=1"
      },
      "page": {
        "limit": 1,
        "start": 0,
        "total": 2
      },
      "series": {
        "items": [
          {
            "metric": "failedBatchCount",
            "timestamp": "2026-03-17T00:00:00Z",
            "value": 3,
            "windowEnd": "2026-03-17T01:00:00Z",
            "windowStart": "2026-03-17T00:00:00Z"
          }
        ],
        "total_items": 1,
        "truncated_items": false
      }
    },
    "status_code": 200,
    "statuses": [],
    "timestamps": {
      "timestamp": "2026-03-17T00:00:00Z",
      "windowEnd": "2026-03-17T01:00:00Z",
      "windowStart": "2026-03-17T00:00:00Z"
    }
  },
  "parser_mode": "endpoint_family",
  "parser_success": true,
  "path": "/data/infrastructure/observability/insights/metrics",
  "query_id": "observability_metrics_pagination",
  "unsupported_api_claim_count": 0,
  "verification": {
    "errors": [],
    "ok": true,
    "unsupported_claims_count": 0,
    "warnings": []
  }
}