{
  "adobe_readiness": {
    "auth_mode": "missing",
    "authorization_constructible": false,
    "credential_ready": false,
    "detected_env_sources": [
      {
        "name": "access_token",
        "source": "missing"
      },
      {
        "name": "api_key",
        "source": "missing"
      },
      {
        "name": "client_id",
        "source": "missing"
      },
      {
        "name": "client_secret",
        "source": "missing"
      },
      {
        "name": "organization",
        "source": "missing"
      },
      {
        "name": "sandbox",
        "source": "missing"
      },
      {
        "name": "base_url",
        "source": "default"
      },
      {
        "name": "scopes",
        "source": "default"
      }
    ],
    "header_constructibility": [
      {
        "constructible": false,
        "header_name": "Authorization"
      },
      {
        "constructible": true,
        "header_name": "Content-Type"
      },
      {
        "constructible": false,
        "header_name": "x-api-key"
      },
      {
        "constructible": false,
        "header_name": "x-gw-ims-org-id"
      },
      {
        "constructible": false,
        "header_name": "x-sandbox-name"
      }
    ],
    "ready_for_live_adobe_api_smoke": false,
    "ready_for_sandbox_endpoints": false,
    "sandbox_ready": false
  },
  "api_state_caveat_forwarded_count": 0,
  "auth_error_count": 0,
  "commands": [
    {
      "command": "python3 scripts/check_adobe_env_local.py",
      "duration_seconds": 1.5091,
      "ended_at": "2026-05-16T21:21:25.573670+00:00",
      "exit_code": 0,
      "report_path": null,
      "started_at": "2026-05-16T21:21:24.064226+00:00",
      "status": "passed"
    },
    {
      "command": "python3 scripts/audit_live_adobe_api_readiness.py",
      "duration_seconds": 1.9783,
      "ended_at": "2026-05-16T21:21:27.551970+00:00",
      "exit_code": 0,
      "report_path": "outputs/reports/live_adobe_api_readiness_audit.json",
      "started_at": "2026-05-16T21:21:25.573888+00:00",
      "status": "passed"
    },
    {
      "command": "python3 scripts/run_live_api_readiness_smoke.py --limit all-safe-get",
      "duration_seconds": 1.6337,
      "ended_at": "2026-05-16T21:21:29.185693+00:00",
      "exit_code": 0,
      "report_path": "outputs/reports/live_api_readiness_smoke.json",
      "started_at": "2026-05-16T21:21:27.552202+00:00",
      "status": "passed"
    },
    {
      "command": "python3 scripts/run_live_api_evidence_pipeline_trial.py",
      "duration_seconds": 1.2876,
      "ended_at": "2026-05-16T21:21:30.473422+00:00",
      "exit_code": 0,
      "report_path": "outputs/reports/live_api_evidence_pipeline_trial.json",
      "started_at": "2026-05-16T21:21:29.185963+00:00",
      "status": "passed"
    },
    {
      "command": "python3 scripts/run_live_api_targeted_failure_analysis.py",
      "duration_seconds": 1.029,
      "ended_at": "2026-05-16T21:21:31.502474+00:00",
      "exit_code": 0,
      "report_path": "outputs/reports/live_api_targeted_failure_analysis.json",
      "started_at": "2026-05-16T21:21:30.473647+00:00",
      "status": "passed"
    }
  ],
  "created_at": "2026-05-16T21:21:31.505629+00:00",
  "credential_ready": false,
  "diagnostic_only": true,
  "endpoint_path_issue_count": 0,
  "external_api_unavailable_count": 0,
  "full_generated_prompt_suite_allowed": false,
  "full_generated_prompt_suite_executed": false,
  "full_live_eval_allowed": false,
  "full_strict_eval_executed": false,
  "guard_decision": "allowed_not_live_mode",
  "live_api_guard_decision": "allowed_not_live_mode",
  "live_api_guard_reason": "not_live_mode",
  "live_empty_count": 0,
  "live_success_count": 0,
  "official_score_claim": false,
  "promotion_allowed": false,
  "reason": "not_live_mode",
  "recommended_followup_commands": [
    "python3 scripts/run_live_api_endpoint_path_diagnosis.py"
  ],
  "recommended_next_command": "python3 scripts/run_live_api_readiness_smoke.py --limit all-safe-get",
  "recommended_next_commands": [
    "python3 scripts/run_live_api_readiness_smoke.py --limit all-safe-get",
    "python3 scripts/run_live_api_endpoint_path_diagnosis.py"
  ],
  "report_type": "post_permission_live_api_verification",
  "safe_rerun_commands": [
    "python3 scripts/run_live_api_readiness_smoke.py --limit all-safe-get",
    "python3 scripts/run_live_api_endpoint_path_diagnosis.py"
  ],
  "sandbox_ready": false,
  "sandbox_scope_issue_count": 0,
  "source_reports": [
    "outputs/reports/live_adobe_api_readiness_audit.json",
    "outputs/reports/live_api_readiness_smoke.json",
    "outputs/reports/live_api_evidence_pipeline_trial.json",
    "outputs/reports/live_api_targeted_failure_analysis.json"
  ],
  "status": "complete",
  "token_acquisition_attempted": false,
  "token_acquisition_ok": false,
  "usable_live_api_evidence_count": 0,
  "waiting_status_report": "outputs/reports/adobe_access_waiting_status.md"
}