{
  "answer_score": 0.505,
  "baseline_answer": "Batch details require live API evidence. Live API verification was not executed because Adobe credentials are unavailable.",
  "current_live_answer": "The API evidence reports batch 01KP69BPA5ZKFB7HCDYPE4GN6F with status/state inactive.",
  "final_score": 0.73,
  "query_id": "example_030",
  "variant_answer": "The API evidence reports batch 01KP69BPA5ZKFB7HCDYPE4GN6F with status/state inactive.",
  "variant_id": "live_api_primary_only_when_required"
}